mcp_calculator_kel/__init__.py
mcp_calculator_kel/__main__.py
mcp_calculator_kel/server.py
moqiqi_weather-0.1.2.dist-info/METADATA
moqiqi_weather-0.1.2.dist-info/WHEEL
moqiqi_weather-0.1.2.dist-info/entry_points.txt
moqiqi_weather-0.1.2.dist-info/RECORD
