Metadata-Version: 2.4
Name: moqiqi-weather
Version: 0.1.2
Summary: a weather search service
Requires-Python: >=3.10
Requires-Dist: build>=1.2.2.post1
Requires-Dist: mcp[cli]>=1.9.2
Requires-Dist: twine>=6.1.0
